jyotishganit/__init__.py
jyotishganit/main.py
jyotishganit/components/__init__.py
jyotishganit/components/ashtakavarga.py
jyotishganit/components/aspects.py
jyotishganit/components/charts.py
jyotishganit/components/divisional_charts.py
jyotishganit/components/houses.py
jyotishganit/components/panchanga.py
jyotishganit/components/states.py
jyotishganit/components/strengths.py
jyotishganit/core/__init__.py
jyotishganit/core/astronomical.py
jyotishganit/core/constants.py
jyotishganit/core/models.py
jyotishganit/core/utils.py
jyotishganit/dasha/__init__.py
jyotishganit/dasha/ashtottari.py
jyotishganit/dasha/vimshottari.py
jyotishganit/dasha/yogini.py
jyotishganit/output/__init__.py
jyotishganit/output/jsonld_formatter.py
jyotishganit-0.1.2.dist-info/licenses/LICENSE
jyotishganit-0.1.2.dist-info/METADATA
jyotishganit-0.1.2.dist-info/WHEEL
jyotishganit-0.1.2.dist-info/top_level.txt
jyotishganit-0.1.2.dist-info/RECORD
