Metadata-Version: 2.4
Name: jyotishganit
Version: 0.1.2
Summary: High precision Vedic astrology calculations in Python
Home-page: https://github.com/northtara/jyotishganit
Author: NorthTara Research
Author-email: NorthTara Research <sid@northtara.ai>
License: MIT
Project-URL: Homepage, https://github.com/northtara/jyotishganit
Project-URL: Documentation, https://github.com/northtara/jyotishganit#readme
Project-URL: Repository, https://github.com/northtara/jyotishganit
Project-URL: Bug Reports, https://github.com/northtara/jyotishganit/issues
Project-URL: Changelog, https://github.com/northtara/jyotishganit/blob/main/CHANGELOG.md
Keywords: astrology,vedic,jyotisha,astronomy,calculations,birth-chart
Classifier: Development Status :: 4 - Beta
Classifier: Intended Audience :: Developers
Classifier: Intended Audience :: Science/Research
Classifier: License :: OSI Approved :: MIT License
Classifier: Operating System :: OS Independent
Classifier: Programming Language :: Python :: 3
Classifier: Programming Language :: Python :: 3.8
Classifier: Programming Language :: Python :: 3.9
Classifier: Programming Language :: Python :: 3.10
Classifier: Programming Language :: Python :: 3.11
Classifier: Programming Language :: Python :: 3.12
Classifier: Topic :: Scientific/Engineering :: Astronomy
Classifier: Topic :: Software Development :: Libraries :: Python Modules
Requires-Python: >=3.8
License-File: LICENSE
Requires-Dist: skyfield>=1.45
Requires-Dist: pandas>=1.3.0
Requires-Dist: numpy>=1.20.0
Provides-Extra: dev
Requires-Dist: pytest>=7.0; extra == "dev"
Requires-Dist: pytest-cov>=4.0; extra == "dev"
Requires-Dist: black>=22.0; extra == "dev"
Requires-Dist: flake8>=5.0; extra == "dev"
Requires-Dist: mypy>=1.0; extra == "dev"
Provides-Extra: docs
Requires-Dist: sphinx>=5.0; extra == "docs"
Requires-Dist: sphinx-rtd-theme>=1.0; extra == "docs"
Dynamic: author
Dynamic: home-page
Dynamic: license-file
Dynamic: requires-python
